{
  "ALSVIN": {
    "LX 2024": 1850000,
    "Luxe 2024": 1870000,
    "DLX 2024": 1899900,
    "Tech 2024": 1919900,
    "Luxe 2025": 2020000,
    "Tech 2025": 2069900
  },
  "EADO PLUS": {
    "LX 2024": 2439900,
    "Luxe 2024": 2459900,
    "DLX 2024": 2509900,
    "Tech 2024": 2529900,
    "Luxe 2025": 2609900,
    "Tech 2025": 2679900
  },
  "LAMORE": {
    "Tech 2024": 2869900
  },
  "CS35 PLUS": {
    "Advance 2024": 2589900,
    "Tech 2024": 2649900,
    "Advance 2025": 2719900,
    "Tech 2025": 2779900
  },
  "UNI-S": {
    "Comfort 2024": 2879900,
    "Luxe 2024": 2939900,
    "Tech 2024": 2999900,
    "Tech+ 2024": 3034900,
    "Comfort 2025": 2989900,
    "Luxe 2025": 3049900,
    "Tech 2025": 3109900,
    "Tech+ 2025": 3144900
  },
  "CS75 PLUS": {
    "1.5AT Comfort 2024": 3590000,
    "2.0AT Luxe 2024": 3790000,
    "2.0AT Tech 2024": 3949900,
     "1.5AT Comfort 2025": 3740000,
    "2.0AT Luxe 2025": 3940000,
    "2.0AT Tech 2025": 4099900
  },
  "CS95 NEW": {
    "DLX 2024": 4529900,
    "Black Edition 2024": 4599900,
    "Tech 2024": 4609900,
    "Tech Black Edition 2024": 4679900,
    "Black Edition 2025": 4749900,
    "Tech 2025": 4759900,
    "Tech Black Edition 2025": 4829900
  },
  "UNI-K": {
    "Luxe 4WD 2024": 4449900,
    "Tech 4WD 2024": 4599900,
    "Tech+ 4WD 2024": 4634900,
    "Comfort 2WD 2025": 4119900,
    "Luxe 4WD 2025": 4549900,
    "Tech 4WD 2025": 4699900,
    "Tech+ 4WD 2025": 4734900
  },
  "UNI-V": {
    "LX 2024": 3119900,
    "Luxe 2024": 3189900,
    "DLX 2024": 3189900,
    "Tech 2024": 3259900,
     "Luxe 2025": 3289900,
    "Tech 2025": 3359900
  },
  "UNI-T": {
    "Luxe 2024": 3069900,
    "Tech 2024": 3169900,
    "Tech_25MY 2024": 3239900,
     "Luxe 2025": 3219900,
    "Tech 2025": 3319900,
    "Tech_25MY 2025": 3389900
  },
  "HUNTER PLUS": {
    "Luxe 2024": 3739900,
    "Luxe 2025": 3889900
  }
}





